design.sv
// Code your design here
module full_subtractor(
  input A,
  input B,
  input Bin,
  output S,
  output Bout
);

  assign S = A ^ B ^ Bin;
  assign Bout = (~A & B & Bin) | (A & ~B & Bin);

endmodule

testbench.sv
// Code your testbench here
// or browse Examples
module tb_full_subtractor;

  reg A;
  reg B;
  reg Bin;
  wire S;
  wire Bout;

  full_subtractor fs(A, B, Bin, S, Bout);

  initial begin
    $dumpfile("full_subtractor.vcd");
    $dumpvars(0, tb_full_subtractor);

    A = 0; B = 0; Bin = 0;
    #10 A = 0; B = 0; Bin = 1;
    #10 A = 0; B = 1; Bin = 0;
    #10 A = 0; B = 1; Bin = 1;
    #10 A = 1; B = 0; Bin = 0;
    #10 A = 1; B = 0; Bin = 1;
    #10 A = 1; B = 1; Bin = 0;
    #10 A = 1; B = 1; Bin = 1;
    #10 $finish;
  end

endmodule

full_subtractor.vcd
$date
	Tue Mar 28 15:20:03 2023
$end
$version
	Icarus Verilog
$end
$timescale
	1s
$end
$scope module tb_full_subtractor $end
$var wire 1 ! Bout $end
$var wire 1 " S $end
$var reg 1 # A $end
$var reg 1 $ B $end
$var reg 1 % Bin $end
$scope module fs $end
$var wire 1 & A $end
$var wire 1 ' B $end
$var wire 1 ( Bin $end
$var wire 1 ! Bout $end
$var wire 1 " S $end
$upscope $end
$upscope $end
$enddefinitions $end
#0
$dumpvars
0(
0'
0&
0%
0$
0#
0"
0!
$end
#10
1"
1%
1(
#20
0%
0(
1$
1'
#30
1!
0"
1%
1(
#40
0!
1"
0%
0(
0$
0'
1#
1&
#50
1!
0"
1%
1(
#60
0!
0%
0(
1$
1'
#70
1"
1%
1(
